Metadata-Version: 2.1
Name: comment-object
Version: 0.0.0
Summary: An explicit object for comments
Home-page: https://github.com/mft/comment
Author: MATSUI Tetsushi
Author-email: matsui.tetsushi@gmail.com
License: UNKNOWN
Keywords: comment
Platform: UNKNOWN
Classifier: Development Status :: 3 - Alpha
Classifier: Intended Audience :: Developers
Classifier: Topic :: Software Development :: Libraries :: Python Modules
Classifier: License :: OSI Approved :: MIT License
Classifier: Programming Language :: Python :: 2
Classifier: Programming Language :: Python :: 2.7
Classifier: Programming Language :: Python :: 3
Requires-Python: >=2.7
